{"cameraMode":{"drawMode":0,"name":"Shaded","section":"Shading Mode"},"sceneLighting":true,"audioPlay":false,"sceneViewState":{"m_AlwaysRefresh":false,"showFog":true,"showSkybox":true,"showFlares":true,"showImageEffects":true,"showParticleSystems":true,"showVisualEffectGraphs":true,"m_FxEnabled":true},"in2DMode":false,"pivot":{"x":-23.74167823791504,"y":88.68634796142578,"z":-172.51596069335938},"rotation":{"x":0.2360590249300003,"y":-0.14080166816711427,"z":0.034591104835271838,"w":0.9608840346336365},"size":19.26161003112793,"orthographic":false}